{
  "generatedAt": "Jun 30 2026",
  "count": 7,
  "rejected": [
    {
      "address": "0x18510d997eba5b8a0102bad7307e70e32bc4ae47",
      "id": null,
      "tier": "watch",
      "reason": "net unprofitable (informed trading is profitable; profit=-3022)"
    },
    {
      "address": "0x6b1fe46602b39d66ef1dea587e386a930dbc3fd0",
      "id": null,
      "tier": "watch",
      "reason": "net unprofitable (informed trading is profitable; profit=-2038)"
    },
    {
      "address": "0xa34429d549f23fe45a9ca5442b79b365cd2f8141",
      "id": null,
      "tier": "watch",
      "reason": "below net-profit floor (profit=$362 < $1000)"
    },
    {
      "address": "0x90134a5c61876dc0f35b72eed743605daae5fc71",
      "id": null,
      "tier": "watch",
      "reason": "net unprofitable (informed trading is profitable; profit=-61947)"
    },
    {
      "address": "0x07d126ea6f8542a58ee2c4c7c31535dd9b3e8ffa",
      "id": null,
      "tier": "watch",
      "reason": "net unprofitable (informed trading is profitable; profit=-1057)"
    },
    {
      "address": "0x97a67e774ef32956d8c3fa8fef543639be872190",
      "id": null,
      "tier": "watch",
      "reason": "net unprofitable (informed trading is profitable; profit=-2696)"
    },
    {
      "address": "0x7b02b2bac2a30ed5e40b7094e734f4c3dc2a4991",
      "id": null,
      "tier": "elevated",
      "reason": "net unprofitable (informed trading is profitable; profit=-54120)"
    }
  ]
}
